CHANGES.yaml
LICENSE
MANIFEST.in
Makefile
README.rst
setup.py
package/__init__.py
package/__init__.pyc
package/errors.py
package/errors.pyc
package/info.py
package/info.pyc
package/info.yaml
package/info.yaml~
package/unittest.py
sunnysunshiney/__init__.py
sunnysunshiney.egg-info/PKG-INFO
sunnysunshiney.egg-info/SOURCES.txt
sunnysunshiney.egg-info/dependency_links.txt
sunnysunshiney.egg-info/top_level.txt
tests/test_import.py