Metadata-Version: 1.1
Name: sunnysunshiney
Version: 0.0.1
Summary: This is your package, 'sunnysunshiney'
Home-page: http://github.com/uniphil/sunnysunshiney-py/
Author: Philip Schleihauf
Author-email: uniphil@gmail.com
License: UNKNOWN
Platform: UNKNOWN
Classifier: Development Status :: 2 - Pre-Alpha
Classifier: License :: OSI Approved :: GNU General Public License v3 (GPLv3)
Classifier: Programming Language :: Python
Classifier: Intended Audience :: Developers
